{
    "target": "192.168.0.1\n",
    "timestamp": "20250503_174436",
    "locations": {
        "timestamp": "2025-05-03 17:44:34",
        "identifier": "192.168.0.1\n",
        "locations": {
            "ip": {
                "error": "All geolocation services failed",
                "details": []
            }
        },
        "data_sources": {
            "online": [],
            "offline": [
                "local_database"
            ]
        },
        "saved_to": "findings\\geo_tracking\\track_20250503_174436.json"
    }
}